Workbook

Sheet شناسایی ریسک
A1: کد ساختار شکست | B1: شرح ریسک | C1: رویداد | D1: پیامد | E1: طبقه بندی ریسک | F1: تأثیر پیامد بر اهداف
A2: KH-RISK-1 | B2: ریسک نبود نقش ها و اختیارات شفاف | C2: در یک پروژه فناورانه، مسئولیت تصمیم گیری بین واحد فناوری، واحد حقوقی و واحد تجاری مشخص نیست و تصمیم نهایی با تأخیر اتخاذ می شود. | D2: تأخیر در تصمیم سازی، افزایش هزینه های هماهنگی، و کاهش اثربخشی حکمرانی فناورانه. | E2: حکمرانی | F2: منفی
A3: KH-RISK-2 | B3: ریسک تعارض منافع در تصمیم گیری فناورانه | C3: یکی از تصمیم گیران، به طور مستقیم یا غیرمستقیم ذی نفع انتخاب یک فناوری یا تأمین کننده خاص است. | D3: انتخاب نامناسب دارایی یا شریک فناورانه، کاهش شفافیت، و خدشه به اعتماد ذی نفعان. | E3: حکمرانی | F3: منفی
A4: KH-RISK-3 | B4: ریسک نبود سازوکار ارزیابی و اولویت بندی تصمیم ها | C4: چند پیشنهاد فناورانه به صورت هم زمان مطرح می شوند اما هیچ چارچوب مشترکی برای ارزیابی ارزش، ریسک و فوریت وجود ندارد. | D4: تخصیص نادرست منابع، اتلاف سرمایه، و از دست رفتن فرصت های باارزش تر. | E4: حکمرانی | F4: منفی
A5: KH-RISK-4 | B5: ریسک دارایی های فناورانه فاقد متولی | C5: یک نمونه اولیه یا فناوری داخلی پس از پایان پروژه، بدون مالک مشخص در سازمان باقی می ماند. | D5: فرسایش تدریجی دارایی، عدم توسعه بیشتر، و احتمال نابودی فرصت تجاری سازی. | E5: دارایی های داخلی | F5: منفی
A6: KH-RISK-5 | B6: ریسک از بین رفتن دانش، مستندات و نمونه ها | C6: پس از خروج یک تیم پروژه، مستندات فنی، کدها یا نمونه های آزمون تحویل و آرشیو نمی شوند. | D6: از دست رفتن قابلیت بازتولید، دشواری توسعه مجدد، و افزایش وابستگی به افراد یا تیم قبلی. | E6: دارایی های داخلی | F6: منفی
A7: KH-RISK-6 | B7: ریسک طبقه بندی نادرست دارایی ها (ارزش، بلوغ، فوریت) | C7: یک دارایی کم ارزش یا کم بلوغ به اشتباه به عنوان دارایی راهبردی اولویت دار طبقه بندی می شود. | D7: انحراف سرمایه گذاری، اتلاف ظرفیت توسعه، و کاهش بازده پرتفوی دارایی های فناورانه. | E7: دارایی های داخلی | F7: منفی
A8: KH-RISK-7 | B8: ریسک تمایلی نداشتن به رها کردن مالکیت دارایی توسط واحدهای سازمانی | C8: یک واحد سازمانی حاضر نیست دارایی فناورانه ای را که دیگر در مأموریتش نیست، به مرکز متولی منتقل کند. | D8: قفل شدن دارایی در یک واحد، جلوگیری از بهره برداری سازمانی، و کاهش سرعت تجاری سازی. | E8: دارایی های داخلی | F8: منفی
A9: KH-RISK-8 | B9: ریسک بسیار تخصصی دارایی های توسعه یافته و بواسطه آن بازار خارجی محدود | C9: دارایی فناورانه ای طراحی می شود که فقط برای یک صنعت یا مشتری بسیار خاص کاربرد دارد. | D9: محدود شدن بازار هدف، دشواری فروش/واگذاری، و کاهش احتمال بازگشت سرمایه. | E9: دارایی های داخلی | F9: منفی
A10: KH-RISK-9 | B10: ریسک قدیمی بودن دارایی ها و نیازمند به روزرسانی های پرهزینه جهت استانداردسازی | C10: دارایی فناورانه داخلی بر پایه فناوری قدیمی ساخته شده و برای ورود به بازار، نیازمند بازطراحی اساسی است. | D10: افزایش هزینه توسعه، طولانی شدن زمان عرضه، و احتمال غیراقتصادی شدن پروژه. | E10: دارایی های داخلی | F10: منفی
A11: KH-RISK-10 | B11: ریسک اعتبار فناورانه و مالی شریک | C11: شریک پیشنهادی در ارائه اسناد فنی یا مالی، سوابق ناکافی یا متناقض دارد. | D11: افزایش احتمال شکست همکاری، ریسک عدم ایفای تعهدات، و هدررفت منابع مشترک. | E11: همکاری های بیرونی | F11: منفی
A12: KH-RISK-11 | B12: ریسک های حقوقی، قراردادی و مالکیتی در مشارکت | C12: در قرارداد مشارکت، مالکیت نتایج تحقیق و توسعه یا حقوق بهره برداری به وضوح تعریف نشده است. | D12: بروز اختلاف حقوقی، توقف پروژه، و کاهش قابلیت بهره برداری از دارایی مشترک. | E12: همکاری های بیرونی | F12: منفی
... A23: KH-RISK-22 | B23: پتانسیل توسعه جریان‌های درآمدی جدید بواسطه نوآورانه بودن طرح کسب‌وکار خوارزمی | C23: ماهیت جدید و نوآورانه طرح‌های کسب‌وکار خوارزمی و پتانسیل آن‌ها برای بازارهای جدید | D23: ایجاد جریان‌های درآمدی تازه و متنوع، افزایش سودآوری و کاهش ریسک وابستگی به درآمدهای سنتی | E23: پایداری و خدمات | F23: مثبت

Sheet سنجش ریسک
A1: شناسه ریسک | B1: شرح ریسک | C1: شدت اثر فعلی | D1: احتمال وقوع فعلی | E1: شدت اثر هدف | F1: احتمال وقوع هدف | G1: واکنش
A2: KH-RISK-1 | B2: =INDEX(r_detect[شرح ریسک],MATCH(r_measure[[#This Row],[شناسه ریسک]],r_detect[کد ساختار شکست],0)) -> ریسک نبود نقش ها و اختیارات شفاف | C2: عمده | D2: ممکن | E2: اساسی | F2: بعید | G2: اجتناب
A3: KH-RISK-2 | B3: =INDEX(r_detect[شرح ریسک],MATCH(r_measure[[#This Row],[شناسه ریسک]],r_detect[کد ساختار شکست],0)) -> ریسک تعارض منافع در تصمیم گیری فناورانه | C3: متوسط | D3: مکرر | E3: عمده | F3: نادر | G3: انتقال | J3: {=_xlfn.UNIQUE(r_measure[شدت اثر هدف])} -> اساسی | K3: {=_xlfn.UNIQUE(r_measure[احتمال وقوع هدف])} -> بعید
A4: KH-RISK-3 | B4: =INDEX(r_detect[شرح ریسک],MATCH(r_measure[[#This Row],[شناسه ریسک]],r_detect[کد ساختار شکست],0)) -> ریسک نبود سازوکار ارزیابی و اولویت بندی تصمیم ها | C4: جزئی | D4: محتمل | E4: متوسط | F4: ممکن | G4: کاهش | J4: عمده | K4: نادر
A5: KH-RISK-4 | B5: =INDEX(r_detect[شرح ریسک],MATCH(r_measure[[#This Row],[شناسه ریسک]],r_detect[کد ساختار شکست],0)) -> ریسک دارایی های فناورانه فاقد متولی | C5: متوسط | D5: بعید | E5: جزئی | F5: محتمل | G5: پذیرش | J5: متوسط | K5: ممکن
A6: KH-RISK-5 | B6: =INDEX(r_detect[شرح ریسک],MATCH(r_measure[[#This Row],[شناسه ریسک]],r_detect[کد ساختار شکست],0)) -> ریسک از بین رفتن دانش، مستندات و نمونه ها | C6: ناچیز | D6: بعید | E6: ناچیز | F6: مکرر | G6: بهره برداری | J6: جزئی | K6: محتمل
A7: KH-RISK-6 | B7: =INDEX(r_detect[شرح ریسک],MATCH(r_measure[[#This Row],[شناسه ریسک]],r_detect[کد ساختار شکست],0)) -> ریسک طبقه بندی نادرست دارایی ها (ارزش، بلوغ، فوریت) | C7: جزئی | D7: بعید | E7: اساسی | F7: بعید | G7: اشتراک گذاری | J7: ناچیز | K7: مکرر
A8: KH-RISK-7 | B8: =INDEX(r_detect[شرح ریسک],MATCH(r_measure[[#This Row],[شناسه ریسک]],r_detect[کد ساختار شکست],0)) -> ریسک تمایلی نداشتن به رها کردن مالکیت دارایی توسط واحدهای سازمانی | C8: عمده | D8: نادر | E8: عمده | F8: نادر | G8: افزایش/تقویت | N8: بعید | O8: نادر | P8: ممکن | Q8: محتمل | R8: مکرر
A9: KH-RISK-8 | B9: =INDEX(r_detect[شرح ریسک],MATCH(r_measure[[#This Row],[شناسه ریسک]],r_detect[کد ساختار شکست],0)) -> ریسک بسیار تخصصی دارایی های توسعه یافته و بواسطه آن بازار خارجی محدود | C9: ناچیز | D9: ممکن | E9: متوسط | F9: ممکن | G9: پذیرش فعال | N9: نادر | O9: بعید | P9: ممکن | Q9: محتمل | R9: مکرر
A10: KH-RISK-9 | B10: =INDEX(r_detect[شرح ریسک],MATCH(r_measure[[#This Row],[شناسه ریسک]],r_detect[کد ساختار شکست],0)) -> ریسک قدیمی بودن دارایی ها و نیازمند به روزرسانی های پرهزینه جهت استانداردسازی | C10: اساسی | D10: محتمل | E10: جزئی | F10: محتمل | G10: اجتناب | P10: ممکن
A11: KH-RISK-10 | B11: =INDEX(r_detect[شرح ریسک],MATCH(r_measure[[#This Row],[شناسه ریسک]],r_detect[کد ساختار شکست],0)) -> ریسک اعتبار فناورانه و مالی شریک | C11: اساسی | D11: مکرر | E11: ناچیز | F11: مکرر | G11: انتقال | Q11: محتمل
A12: KH-RISK-11 | B12: =INDEX(r_detect[شرح ریسک],MATCH(r_measure[[#This Row],[شناسه ریسک]],r_detect[کد ساختار شکست],0)) -> ریسک های حقوقی، قراردادی و مالکیتی در مشارکت | C12: عمده | D12: مکرر | E12: اساسی | F12: بعید | G12: کاهش | J12: اساسی | K12: بعید
A13: KH-RISK-12 | B13: =INDEX(r_detect[شرح ریسک],MATCH(r_measure[[#This Row],[شناسه ریسک]],r_detect[کد ساختار شکست],0)) -> ریسک عدم هم راستایی اهداف شریک با منافع خوارزمی | C13: متوسط | D13: مکرر | E13: عمده | F13: نادر | G13: پذیرش | J13: عمده | K13: نادر
A14: KH-RISK-13 | B14: =INDEX(r_detect[شرح ریسک],MATCH(r_measure[[#This Row],[شناسه ریسک]],r_detect[کد ساختار شکست],0)) -> ریسک پراکندگی دانش و فقدان نظام یکپارچه | C14: ناچیز | D14: ممکن | E14: متوسط | F14: ممکن | G14: بهره برداری | J14: متوسط | K14: ممکن
A15: KH-RISK-14 | B15: =INDEX(r_detect[شرح ریسک],MATCH(r_measure[[#This Row],[شناسه ریسک]],r_detect[کد ساختار شکست],0)) -> ریسک وابستگی به افراد کلیدی | C15: جزئی | D15: ممکن | E15: جزئی | F15: محتمل | G15: اشتراک گذاری | J15: جزئی | K15: محتمل
A16: KH-RISK-15 | B16: =INDEX(r_detect[شرح ریسک],MATCH(r_measure[[#This Row],[شناسه ریسک]],r_detect[کد ساختار شکست],0)) -> ریسک تولید دانش غیرمعتبر یا غیرکاربردی | C16: عمده | D16: مکرر | E16: ناچیز | F16: مکرر | G16: افزایش/تقویت | J16: ناچیز | K16: مکرر
A17: KH-RISK-16 | B17: =INDEX(r_detect[شرح ریسک],MATCH(r_measure[[#This Row],[شناسه ریسک]],r_detect[کد ساختار شکست],0)) -> ریسک های نقدینگی و ناپایداری درآمد | C17: متوسط | D17: ممکن | E17: اساسی | F17: بعید | G17: پذیرش فعال
A18: KH-RISK-17 | B18: =INDEX(r_detect[شرح ریسک],MATCH(r_measure[[#This Row],[شناسه ریسک]],r_detect[کد ساختار شکست],0)) -> ریسک های آسیب به برند مرجع | C18: اساسی | D18: محتمل | E18: عمده | F18: نادر | G18: اشتراک گذاری
A19: KH-RISK-18 | B19: =INDEX(r_detect[شرح ریسک],MATCH(r_measure[[#This Row],[شناسه ریسک]],r_detect[کد ساختار شکست],0)) -> ریسک افت کیفیت خدمات پشتیبانی دارایی محور | C19: اساسی | D19: نادر | E19: متوسط | F19: ممکن | G19: افزایش/تقویت
A20: KH-RISK-19 | B20: =INDEX(r_detect[شرح ریسک],MATCH(r_measure[[#This Row],[شناسه ریسک]],r_detect[کد ساختار شکست],0)) -> تجربه مفید مدیرعامل در اکوسیستم دانشگاهی | C20: متوسط | D20: بعید | E20: جزئی | F20: محتمل | G20: پذیرش فعال
A21: KH-RISK-20 | B21: =INDEX(r_detect[شرح ریسک],MATCH(r_measure[[#This Row],[شناسه ریسک]],r_detect[کد ساختار شکست],0)) -> سابقه کار اجرایی مدیران ارشد در صنعت پتروشیمی | C21: عمده | D21: محتمل | E21: ناچیز | F21: مکرر | G21: کاهش
A22: KH-RISK-21 | B22: =INDEX(r_detect[شرح ریسک],MATCH(r_measure[[#This Row],[شناسه ریسک]],r_detect[کد ساختار شکست],0)) -> هم‌افزایی تجربه صنعتی و دانش دانشگاهی | C22: ناچیز | D22: ممکن | E22: عمده | F22: محتمل | G22: پذیرش
A23: KH-RISK-22 | B23: =INDEX(r_detect[شرح ریسک],MATCH(r_measure[[#This Row],[شناسه ریسک]],r_detect[کد ساختار شکست],0)) -> پتانسیل توسعه جریان‌های درآمدی جدید بواسطه نوآورانه بودن طرح کسب‌وکار خوارزمی | C23: جزئی | D23: نادر | E23: عمده | F23: محتمل | G23: پذیرش فعال

Sheet Heat Map
D1: ماتریس ریسک (تأثیر منفی)
A2: شدت \ احتمال | B2: نادر | C2: بعید | D2: ممکن | E2: محتمل | F2: مکرر
A3: اساسی | B3: Medium | C3: Medium | D3: High | E3: Critical | F3: Critical
A4: عمده | B4: Low | C4: Medium | D4: High | E4: Critical | F4: Critical
A5: متوسط | B5: Low | C5: Medium | D5: Medium | E5: High | F5: High
A6: جزئی | B6: Low | C6: Medium | D6: Medium | E6: Medium | F6: Medium
A7: ناچیز | B7: Low | C7: Low | D7: Low | E7: Low | F7: Medium
D9: ماتریس ریسک (تأثیر مثبت)
A10: شدت \ احتمال | B10: نادر | C10: بعید | D10: ممکن | E10: محتمل | F10: مکرر
A11: اساسی | B11: Medium | C11: Medium | D11: High | E11: Critical | F11: Critical
A12: عمده | B12: Low | C12: Medium | D12: High | E12: Critical | F12: Critical
A13: متوسط | B13: Low | C13: Medium | D13: Medium | E13: High | F13: High
A14: جزئی | B14: Low | C14: Medium | D14: Medium | E14: Medium | F14: Medium
A15: ناچیز | B15: Low | C15: Low | D15: Low | E15: Low | F15: Medium
A18: ماتریس واکنش به ریسک
A19: ردیف | B19: شرح واکنش | C19: نوع ریسک
A20: 1 | B20: اجتناب | C20: منفی
A21: 2 | B21: انتقال | C21: منفی
A22: 3 | B22: کاهش | C22: منفی
A23: 4 | B23: پذیرش | C23: منفی
A24: 5 | B24: بهره برداری | C24: مثبت
A25: 6 | B25: اشتراک گذاری | C25: مثبت
A26: 7 | B26: افزایش/تقویت | C26: مثبت
A27: 8 | B27: پذیرش فعال | C27: مثبت
A32: ردیف | B32: شرح ریسک مثبت | C32: توضیحات | D32: کاربرد در خوارزمی | E32: اقدام
A33: 1 | B33: بهره‌برداری (Exploit) | C33: این استراتژی زمانی استفاده می‌شود که سازمان می‌خواهد قطعیتِ رخ دادنِ فرصت** را به ۱۰۰٪ برساند. در اینجا شما به دنبال «ربودن» فرصت هستید. | D33: فرض کنید فرصتی برای اجرای یک پروژه مطالعاتی نوآورانه با همکاری یک دانشگاه معتبر وجود دارد. | E33: اختصاص بهترین تیم فنی و منابع مالی اختصاصی به این پروژه تا اطمینان حاصل شود که این فرصت حتماً به درآمد یا صرفه‌جویی تبدیل می‌شود.
A34: 2 | B34: اشتراک‌گذاری (Share) | C34: وقتی سازمان به تنهایی نمی‌تواند از تمام ظرفیت یک فرصت استفاده کند یا برای استفاده بهتر نیاز به دانش مکمل دارد، از این استراتژی استفاده می‌شود. | D34: در بخش «درآمد حاصل از مشارکت» یا «فروش خدمات اکوسیستم نوآوری». | E34: ایجاد مشارکت با یک شرکت فناور دیگر (Joint Venture) برای اجرای پروژه‌ای که سودآوری بالایی دارد، به‌طوری‌که هم خوارزمی و هم شریکش از آن سود ببرند. تقسیم ریسک و سود، شانس موفقیت را افزایش می‌دهد.
A35: 3 | B35: افزایش/تقویت (Enhance) | C35: اگر نمی‌توانید وقوع فرصت را تضمین کنید، هدف این است که احتمال وقوع یا میزان تأثیر مثبت آن را افزایش دهید. | D35: در «صرفه‌جویی ارزش‌گذاری‌شده داخلی». | E35: برای اینکه صرفه‌جویی حاصل از استفاده از تجهیزات فعلی بجای خرید تجهیزات جدید افزایش یابد، واحد مالی می‌تواند با بهبود فرآیندهای نگهداری و تعمیرات (HSE)، نرخ در دسترس بودن تجهیزات را افزایش دهد تا آن «صرفه‌جویی» بزرگتر شود.
A36: 4 | B36: پذیرش فعال (Accept) | C36: گاهی اوقات یک فرصت پیش می‌آید که انجام اقدام پیشگیرانه برای آن هزینه بیشتری از سودش دارد. در اینجا شما فرصت را «می‌پذیرید» اما برای بهره‌برداری از آن «آمادگی» دارید. | D36: نوسانات مثبت در بازار لایسنس‌دهی بیرونی. | E36: سازمان استراتژی مشخصی برای آن ندارد، اما اگر فرصتی پیش آمد، تیم فروش و قراردادها آماده است که سریعاً وارد عمل شده و از آن سود کسب کند.
A39: حکمرانی
A40: دارایی های داخلی
A41: همکاری های بیرونی
A42: مرجعیت فکری
A43: پایداری و خدمات

Sheet اقدامات
A1: شناسه ریسک | B1: شرح اقدام | C1: ماه/بازه | D1: تاریخ شروع | E1: تاریخ پایان | F1: پیشرفت اجرا (%) | G1: اهمیت (1-10) | H1: مدت زمان | I1: درصد وزنی | J1: پیشرفت فیزیکی
A2: KH-RISK-1 | B2: تعریف RACI برای «تصمیم های فناورانه/سرمایه گذاری دارایی محور» و نگاشت به ساختار سازمان | C2: فروردین | D2: 46102 | E2: 46132 | F2: 0.9 | G2: 4 | H2: =r_actions[[#This Row],[تاریخ پایان]]-r_actions[[#This Row],[تاریخ شروع]] -> 30 | I2: =r_actions[[#This Row],[مدت زمان]]/365 -> 0.082191781 | J2: =r_actions[[#This Row],[درصد وزنی]]*r_actions[[#This Row],[پیشرفت اجرا (%)]] -> 0.073972603
A3: KH-RISK-1 | B3: تصویب کارگروه/کمیته تصمیم گیری (TB/SC) + ابلاغ اختیارها و مسیر اخذ تصمیم | C3: اردیبهشت | D3: 46133 | E3: 46163 | F3: 0.9 | G3: 1 | H3: =r_actions[[#This Row],[تاریخ پایان]]-r_actions[[#This Row],[تاریخ شروع]] -> 30 | I3: =r_actions[[#This Row],[مدت زمان]]/365 -> 0.082191781 | J3: =r_actions[[#This Row],[درصد وزنی]]*r_actions[[#This Row],[پیشرفت اجرا (%)]] -> 0.073972603
A4: KH-RISK-1 | B4: تعیین SLA برای زمان تصمیم (مثلاً ۱۰ روز کاری) و ثبت گردش کار | C4: خرداد | D4: 46164 | E4: 46194 | F4: 0.9 | G4: 5 | H4: =r_actions[[#This Row],[تاریخ پایان]]-r_actions[[#This Row],[تاریخ شروع]] -> 30 | I4: =r_actions[[#This Row],[مدت زمان]]/365 -> 0.082191781 | J4: =r_actions[[#This Row],[درصد وزنی]]*r_actions[[#This Row],[پیشرفت اجرا (%)]] -> 0.073972603
A5: KH-RISK-1 | B5: مانیتورینگ ماهانه «عدم تطابق نقش ها/تأخیر تصمیم» و گزارش به هیئت/کمیته حکمرانی | C5: تیر تا اسفند | D5: 46195 | E5: 46466 | F5: 0.12 | G5: 3 | H5: =r_actions[[#This Row],[تاریخ پایان]]-r_actions[[#This Row],[تاریخ شروع]] -> 271 | I5: =r_actions[[#This Row],[مدت زمان]]/365 -> 0.74246575 | J5: =r_actions[[#This Row],[درصد وزنی]]*r_actions[[#This Row],[پیشرفت اجرا (%)]] -> 0.08909589
A6: KH-RISK-2 | B6: تدوین «سیاست تعارض منافع» (تعریف ذی نفع، فرآیند افشا، محرومیت از رأی) | C6: فروردین | D6: 46102 | E6: 46132 | F6: 0.23 | G6: 9 | H6: =r_actions[[#This Row],[تاریخ پایان]]-r_actions[[#This Row],[تاریخ شروع]] -> 30 | I6: =r_actions[[#This Row],[مدت زمان]]/365 -> 0.082191781 | J6: =r_actions[[#This Row],[درصد وزنی]]*r_actions[[#This Row],[پیشرفت اجرا (%)]] -> 0.01890411
A7: KH-RISK-2 | B7: ایجاد فرم افشای سالانه + چک لیست تعارض منافع برای هر تصمیم/پروژه | C7: اردیبهشت | D7: 46133 | E7: 46163 | F7: 0.34 | G7: 5 | H7: =r_actions[[#This Row],[تاریخ پایان]]-r_actions[[#This Row],[تاریخ شروع]] -> 30 | I7: =r_actions[[#This Row],[مدت زمان]]/365 -> 0.082191781 | J7: =r_actions[[#This Row],[درصد وزنی]]*r_actions[[#This Row],[پیشرفت اجرا (%)]] -> 0.027945205
A8: KH-RISK-2 | B8: آموزش تصمیم گیران و اجرای پایلوت روی ۲ پروژه/تصمیم | C8: خرداد | D8: 46164 | E8: 46194 | F8: 0.45 | G8: 2 | H8: =r_actions[[#This Row],[تاریخ پایان]]-r_actions[[#This Row],[تاریخ شروع]] -> 30 | I8: =r_actions[[#This Row],[مدت زمان]]/365 -> 0.082191781 | J8: =r_actions[[#This Row],[درصد وزنی]]*r_actions[[#This Row],[پیشرفت اجرا (%)]] -> 0.036986301
A9: KH-RISK-2 | B9: اجرای ماهانه کنترل: تطابق افشاها با تصمیم های ثبت شده + بازبینی نمونه ای | C9: تیر تا اسفند | D9: 46195 | E9: 46466 | F9: 0.46 | G9: 6 | H9: =r_actions[[#This Row],[تاریخ پایان]]-r_actions[[#This Row],[تاریخ شروع]] -> 271 | I9: =r_actions[[#This Row],[مدت زمان]]/365 -> 0.74246575 | J9: =r_actions[[#This Row],[درصد وزنی]]*r_actions[[#This Row],[پیشرفت اجرا (%)]] -> 0.34153425
A10: KH-RISK-3 | B10: طراحی چارچوب اولویت بندی (ارزش/ریسک/هزینه/فوریت/هم راستایی با فازها) | C10: فروردین | D10: 46102 | E10: 46132 | F10: 0.58 | G10: 4 | H10: =r_actions[[#This Row],[تاریخ پایان]]-r_actions[[#This Row],[تاریخ شروع]] -> 30 | I10: =r_actions[[#This Row],[مدت زمان]]/365 -> 0.082191781 | J10: =r_actions[[#This Row],[درصد وزنی]]*r_actions[[#This Row],[پیشرفت اجرا (%)]] -> 0.047671233
A11: KH-RISK-3 | B11: تعریف مدل امتیازدهی و معیارهای وزن دهی (Risk-Value-Fit) | C11: اردیبهشت | D11: 46133 | E11: 46163 | F11: 0.68 | G11: 5 | H11: =r_actions[[#This Row],[تاریخ پایان]]-r_actions[[#This Row],[تاریخ شروع]] -> 30 | I11: =r_actions[[#This Row],[مدت زمان]]/365 -> 0.082191781 | J11: =r_actions[[#This Row],[درصد وزنی]]*r_actions[[#This Row],[پیشرفت اجرا (%)]] -> 0.055890411
A12: KH-RISK-3 | B12: اجرای مدل روی سبد پیشنهادی برای ۱۴۰۵ و تعیین «پایپ لاین» پروژه ها | C12: خرداد | D12: 46164 | E12: 46194 | F12: 0.78 | G12: 6 | H12: =r_actions[[#This Row],[تاریخ پایان]]-r_actions[[#This Row],[تاریخ شروع]] -> 30 | I12: =r_actions[[#This Row],[مدت زمان]]/365 -> 0.082191781 | J12: =r_actions[[#This Row],[درصد وزنی]]*r_actions[[#This Row],[پیشرفت اجرا (%)]] -> 0.064109589
A13: KH-RISK-3 | B13: جلسه ماهانه کمیته ارزیابی + به روزرسانی ورودی ها (Demand/Cost/Risk)، گزارش اختلاف امتیاز با خروجی تصمیم | C13: تیر تا اسفند | D13: 46195 | E13: 46466 | F13: 0.83 | G13: 2 | H13: =r_actions[[#This Row],[تاریخ پایان]]-r_actions[[#This Row],[تاریخ شروع]] -> 271 | I13: =r_actions[[#This Row],[مدت زمان]]/365 -> 0.74246575 | J13: =r_actions[[#This Row],[درصد وزنی]]*r_actions[[#This Row],[پیشرفت اجرا (%)]] -> 0.61624658
... A74: KH-RISK-19 | B74: شناسایی و تدوین لیست اولویت‌دار مراکز دانشگاهی و پروژه‌های کلیدی | C74: فروردین تا خرداد | D74: 46102 | E74: 46194 | F74: 0.9 | G74: 1 | H74: =r_actions[[#This Row],[تاریخ پایان]]-r_actions[[#This Row],[تاریخ شروع]] -> 92 | I74: =r_actions[[#This Row],[مدت زمان]]/365 -> 0.25205479 | J74: =r_actions[[#This Row],[درصد وزنی]]*r_actions[[#This Row],[پیشرفت اجرا (%)]] -> 0.22684932
A75: KH-RISK-19 | B75: برگزاری جلسات سطح بالا با رؤسای دانشگاه‌ها و مراکز جهت جذب پروژه‌ها | C75: تیر تا شهریور | D75: 46195 | E75: =r_actions[[#This Row],[تاریخ شروع]]+92 -> 46287 | F75: 0.12 | G75: 2 | H75: =r_actions[[#This Row],[تاریخ پایان]]-r_actions[[#This Row],[تاریخ شروع]] -> 92 | I75: =r_actions[[#This Row],[مدت زمان]]/365 -> 0.25205479 | J75: =r_actions[[#This Row],[درصد وزنی]]*r_actions[[#This Row],[پیشرفت اجرا (%)]] -> 0.030246575
A76: KH-RISK-19 | B76: نهایی‌سازی تفاهم‌نامه‌های همکاری و جذب رسمی پروژه‌های دانش‌بنیان | C76: مهر تا آذر | D76: =E75 -> 46287 | E76: =r_actions[[#This Row],[تاریخ شروع]]+90 -> 46377 | F76: 0.23 | G76: 1 | H76: =r_actions[[#This Row],[تاریخ پایان]]-r_actions[[#This Row],[تاریخ شروع]] -> 90 | I76: =r_actions[[#This Row],[مدت زمان]]/365 -> 0.24657534 | J76: =r_actions[[#This Row],[درصد وزنی]]*r_actions[[#This Row],[پیشرفت اجرا (%)]] -> 0.056712329
A77: KH-RISK-19 | B77: آغاز عملیاتی پروژه‌ها و پایش پیشرفت آن‌ها | C77: دی تا اسفند | D77: =E76 -> 46377 | E77: =r_actions[[#This Row],[تاریخ شروع]]+89 -> 46466 | F77: 0.34 | G77: 9 | H77: =r_actions[[#This Row],[تاریخ پایان]]-r_actions[[#This Row],[تاریخ شروع]] -> 89 | I77: =r_actions[[#This Row],[مدت زمان]]/365 -> 0.24383562 | J77: =r_actions[[#This Row],[درصد وزنی]]*r_actions[[#This Row],[پیشرفت اجرا (%)]] -> 0.08290411
A78: KH-RISK-20 | B78: تشکیل کمیته راهبری فنی با حضور مدیران ارشد | C78: فروردین تا اردیبهشت | D78: 46102 | E78: 46163 | F78: 0.45 | G78: 4 | H78: =r_actions[[#This Row],[تاریخ پایان]]-r_actions[[#This Row],[تاریخ شروع]] -> 61 | I78: =r_actions[[#This Row],[مدت زمان]]/365 -> 0.16712329 | J78: =r_actions[[#This Row],[درصد وزنی]]*r_actions[[#This Row],[پیشرفت اجرا (%)]] -> 0.075205479
A79: KH-RISK-20 | B79: تدوین چک‌لیست‌های ارزیابی پروژه بر اساس تجارب مدیران | C79: خرداد تا مرداد | D79: 46164 | E79: =r_actions[[#This Row],[تاریخ شروع]]+92 -> 46256 | F79: 0.46 | G79: 7 | H79: =r_actions[[#This Row],[تاریخ پایان]]-r_actions[[#This Row],[تاریخ شروع]] -> 92 | I79: =r_actions[[#This Row],[مدت زمان]]/365 -> 0.25205479 | J79: =r_actions[[#This Row],[درصد وزنی]]*r_actions[[#This Row],[پیشرفت اجرا (%)]] -> 0.11594521
A80: KH-RISK-20 | B80: ارزیابی مستمر پروژه‌های جاری و اعمال اصلاحات استراتژیک. | C80: شهریور تا آبان | D80: =E79+1 -> 46257 | E80: =r_actions[[#This Row],[تاریخ شروع]]+90 -> 46347 | F80: 0.58 | G80: 3 | H80: =r_actions[[#This Row],[تاریخ پایان]]-r_actions[[#This Row],[تاریخ شروع]] -> 90 | I80: =r_actions[[#This Row],[مدت زمان]]/365 -> 0.24657534 | J80: =r_actions[[#This Row],[درصد وزنی]]*r_actions[[#This Row],[پیشرفت اجرا (%)]] -> 0.1430137
A81: KH-RISK-20 | B81: برگزاری جلسات انتقال تجربه و بازبینی مدل‌های تجاری‌سازی | C81: آذر تا اسفند | D81: =E80+1 -> 46348 | E81: =r_actions[[#This Row],[تاریخ شروع]]+118 -> 46466 | F81: 0.68 | G81: 7 | H81: =r_actions[[#This Row],[تاریخ پایان]]-r_actions[[#This Row],[تاریخ شروع]] -> 118 | I81: =r_actions[[#This Row],[مدت زمان]]/365 -> 0.32328767 | J81: =r_actions[[#This Row],[درصد وزنی]]*r_actions[[#This Row],[پیشرفت اجرا (%)]] -> 0.21983562
A82: KH-RISK-21 | B82: فراخوان برای تشکیل کارگروه‌های مشترک صنعت و دانشگاه. | C82: فروردین تا خرداد | D82: 46102 | E82: 46194 | F82: 0.78 | G82: 3 | H82: =r_actions[[#This Row],[تاریخ پایان]]-r_actions[[#This Row],[تاریخ شروع]] -> 92 | I82: =r_actions[[#This Row],[مدت زمان]]/365 -> 0.25205479 | J82: =r_actions[[#This Row],[درصد وزنی]]*r_actions[[#This Row],[پیشرفت اجرا (%)]] -> 0.19660274
A83: KH-RISK-21 | B83: تعریف پروژه‌های پایلوت و تخصیص منابع انسانی از هر دو بخش (دانشگاهی و صنعتی). | C83: تیر تا مهر | D83: 46195 | E83: =r_actions[[#This Row],[تاریخ شروع]]+122 -> 46317 | F83: 0.83 | G83: 4 | H83: =r_actions[[#This Row],[تاریخ پایان]]-r_actions[[#This Row],[تاریخ شروع]] -> 122 | I83: =r_actions[[#This Row],[مدت زمان]]/365 -> 0.33424658 | J83: =r_actions[[#This Row],[درصد وزنی]]*r_actions[[#This Row],[پیشرفت اجرا (%)]] -> 0.27742466
A84: KH-RISK-21 | B84: پایش هم‌افزایی و گزارش میزان کاهش فاصله ایده تا اجرا. | C84: آبان تا دی | D84: =E83+1 -> 46318 | E84: =r_actions[[#This Row],[تاریخ شروع]]+89 -> 46407 | F84: 0 | G84: 10 | H84: =r_actions[[#This Row],[تاریخ پایان]]-r_actions[[#This Row],[تاریخ شروع]] -> 89 | I84: =r_actions[[#This Row],[مدت زمان]]/365 -> 0.24383562 | J84: =r_actions[[#This Row],[درصد وزنی]]*r_actions[[#This Row],[پیشرفت اجرا (%)]] -> 0
A85: KH-RISK-21 | B85: مستندسازی دستاوردها و تکرار مدل در سایر پروژه‌ها. | C85: بهمن تا اسفند | D85: =E84+1 -> 46408 | E85: =r_actions[[#This Row],[تاریخ شروع]]+58 -> 46466 | F85: 0.46 | G85: 7 | H85: =r_actions[[#This Row],[تاریخ پایان]]-r_actions[[#This Row],[تاریخ شروع]] -> 58 | I85: =r_actions[[#This Row],[مدت زمان]]/365 -> 0.15890411 | J85: =r_actions[[#This Row],[درصد وزنی]]*r_actions[[#This Row],[پیشرفت اجرا (%)]] -> 0.07309589
A86: KH-RISK-22 | B86: پایش دائمی بازارهای هدف برای شناسایی تقاضاهای جدید | C86: فروردین تا خرداد | D86: 46102 | E86: 46194 | F86: 0.58 | G86: 3 | H86: =r_actions[[#This Row],[تاریخ پایان]]-r_actions[[#This Row],[تاریخ شروع]] -> 92 | I86: =r_actions[[#This Row],[مدت زمان]]/365 -> 0.25205479 | J86: =r_actions[[#This Row],[درصد وزنی]]*r_actions[[#This Row],[پیشرفت اجرا (%)]] -> 0.14619178
A87: KH-RISK-22 | B87: بررسی دوره‌ای مدل‌های درآمدی در جلسات هیئت‌مدیره. | C87: تیر تا شهریور | D87: 46195 | E87: =r_actions[[#This Row],[تاریخ شروع]]+92 -> 46287 | F87: 0.68 | G87: 7 | H87: =r_actions[[#This Row],[تاریخ پایان]]-r_actions[[#This Row],[تاریخ شروع]] -> 92 | I87: =r_actions[[#This Row],[مدت زمان]]/365 -> 0.25205479 | J87: =r_actions[[#This Row],[درصد وزنی]]*r_actions[[#This Row],[پیشرفت اجرا (%)]] -> 0.17139726
A88: KH-RISK-22 | B88: اختصاص بودجه احتیاطی (بافر) برای ورود سریع به فرصت‌های شناسایی شده | C88: مهر تا آذر | D88: =E87 -> 46287 | E88: =r_actions[[#This Row],[تاریخ شروع]]+90 -> 46377 | F88: 0 | G88: 2 | H88: =r_actions[[#This Row],[تاریخ پایان]]-r_actions[[#This Row],[تاریخ شروع]] -> 90 | I88: =r_actions[[#This Row],[مدت زمان]]/365 -> 0.24657534 | J88: =r_actions[[#This Row],[درصد وزنی]]*r_actions[[#This Row],[پیشرفت اجرا (%)]] -> 0
A89: KH-RISK-22 | B89: تحلیل نهایی میزان تحقق درآمدها و بازنگری در طرح کسب‌وکار | C89: دی تا اسفند | D89: =E88 -> 46377 | E89: =r_actions[[#This Row],[تاریخ شروع]]+89 -> 46466 | F89: 0 | G89: 1 | H89: =r_actions[[#This Row],[تاریخ پایان]]-r_actions[[#This Row],[تاریخ شروع]] -> 89 | I89: =r_actions[[#This Row],[مدت زمان]]/365 -> 0.24383562 | J89: =r_actions[[#This Row],[درصد وزنی]]*r_actions[[#This Row],[پیشرفت اجرا (%)]] -> 0

Sheet ارزیابی
A1: شناسه ریسک | B1: شرح ریسک | C1: تأثیر | D1: طبقه بندی | E1: شدت اثر فعلی | F1: احتمال وقوع فعلی | G1: سطح فعلی ریسک | H1: شدت اثر هدف | I1: احتمال وقوع هدف | J1: سطح هدف ریسک | K1: پیشرفت فیزیکی
A2: KH-RISK-1 | B2: =INDEX(r_detect[شرح ریسک],MATCH(Table1[[#This Row],[شناسه ریسک]],r_detect[کد ساختار شکست],0)) -> ریسک نبود نقش ها و اختیارات شفاف | C2: منفی | D2: =INDEX(r_detect[طبقه بندی ریسک],MATCH(Table1[[#This Row],[شناسه ریسک]],r_detect[کد ساختار شکست],0)) -> حکمرانی | E2: =INDEX(r_measure[شدت اثر فعلی],MATCH(Table1[[#This Row],[شناسه ریسک]],r_measure[شناسه ریسک],0)) -> عمده | F2: =INDEX(r_measure[احتمال وقوع فعلی],MATCH(Table1[[#This Row],[شناسه ریسک]],r_measure[شناسه ریسک],0)) -> ممکن | G2: =INDEX('Heat Map'!$B$3:$F$7, MATCH(E2,'Heat Map'!$A$3:$A$7, 0), MATCH(F2,'Heat Map'!$B$2:$F$2, 0)) -> High | H2: =INDEX(r_measure[شدت اثر هدف],MATCH(Table1[[#This Row],[شناسه ریسک]],r_measure[شناسه ریسک],0)) -> اساسی | I2: =INDEX(r_measure[احتمال وقوع هدف],MATCH(Table1[[#This Row],[شناسه ریسک]],r_measure[شناسه ریسک],0)) -> بعید | J2: =INDEX('Heat Map'!$B$3:$F$7, MATCH(H2,'Heat Map'!$A$11:$A$15, 0), MATCH(I2,'Heat Map'!$B$10:$F$10, 0)) -> Medium | K2: {=SUMPRODUCT(_xlfn._xlws.FILTER(r_actions[پیشرفت فیزیکی],r_actions[شناسه ریسک]=Table1[[#This Row],[شناسه ریسک]]),_xlfn._xlws.FILTER(r_actions[پیشرفت اجرا (%)],r_actions[شناسه ریسک]=Table1[[#This Row],[شناسه ریسک]]))} -> 0.21041753
A3: KH-RISK-2 | B3: =INDEX(r_detect[شرح ریسک],MATCH(Table1[[#This Row],[شناسه ریسک]],r_detect[کد ساختار شکست],0)) -> ریسک تعارض منافع در تصمیم گیری فناورانه | C3: منفی | D3: =INDEX(r_detect[طبقه بندی ریسک],MATCH(Table1[[#This Row],[شناسه ریسک]],r_detect[کد ساختار شکست],0)) -> حکمرانی | E3: =INDEX(r_measure[شدت اثر فعلی],MATCH(Table1[[#This Row],[شناسه ریسک]],r_measure[شناسه ریسک],0)) -> متوسط | F3: =INDEX(r_measure[احتمال وقوع فعلی],MATCH(Table1[[#This Row],[شناسه ریسک]],r_measure[شناسه ریسک],0)) -> مکرر | G3: =INDEX('Heat Map'!$B$3:$F$7, MATCH(E3,'Heat Map'!$A$3:$A$7, 0), MATCH(F3,'Heat Map'!$B$2:$F$2, 0)) -> High | H3: =INDEX(r_measure[شدت اثر هدف],MATCH(Table1[[#This Row],[شناسه ریسک]],r_measure[شناسه ریسک],0)) -> عمده | I3: =INDEX(r_measure[احتمال وقوع هدف],MATCH(Table1[[#This Row],[شناسه ریسک]],r_measure[شناسه ریسک],0)) -> نادر | J3: =INDEX('Heat Map'!$B$3:$F$7, MATCH(H3,'Heat Map'!$A$11:$A$15, 0), MATCH(I3,'Heat Map'!$B$10:$F$10, 0)) -> Low | K3: {=SUMPRODUCT(_xlfn._xlws.FILTER(r_actions[پیشرفت فیزیکی],r_actions[شناسه ریسک]=Table1[[#This Row],[شناسه ریسک]]),_xlfn._xlws.FILTER(r_actions[پیشرفت اجرا (%)],r_actions[شناسه ریسک]=Table1[[#This Row],[شناسه ریسک]]))} -> 0.1875989
A4: KH-RISK-3 | B4: =INDEX(r_detect[شرح ریسک],MATCH(Table1[[#This Row],[شناسه ریسک]],r_detect[کد ساختار شکست],0)) -> ریسک نبود سازوکار ارزیابی و اولویت بندی تصمیم ها | C4: منفی | D4: =INDEX(r_detect[طبقه بندی ریسک],MATCH(Table1[[#This Row],[شناسه ریسک]],r_detect[کد ساختار شکست],0)) -> حکمرانی | E4: =INDEX(r_measure[شدت اثر فعلی],MATCH(Table1[[#This Row],[شناسه ریسک]],r_measure[شناسه ریسک],0)) -> جزئی | F4: =INDEX(r_measure[احتمال وقوع فعلی],MATCH(Table1[[#This Row],[شناسه ریسک]],r_measure[شناسه ریسک],0)) -> محتمل | G4: =INDEX('Heat Map'!$B$3:$F$7, MATCH(E4,'Heat Map'!$A$3:$A$7, 0), MATCH(F4,'Heat Map'!$B$2:$F$2, 0)) -> Medium | H4: =INDEX(r_measure[شدت اثر هدف],MATCH(Table1[[#This Row],[شناسه ریسک]],r_measure[شناسه ریسک],0)) -> متوسط | I4: =INDEX(r_measure[احتمال وقوع هدف],MATCH(Table1[[#This Row],[شناسه ریسک]],r_measure[شناسه ریسک],0)) -> ممکن | J4: =INDEX('Heat Map'!$B$3:$F$7, MATCH(H4,'Heat Map'!$A$11:$A$15, 0), MATCH(I4,'Heat Map'!$B$10:$F$10, 0)) -> Medium | K4: {=SUMPRODUCT(_xlfn._xlws.FILTER(r_actions[پیشرفت فیزیکی],r_actions[شناسه ریسک]=Table1[[#This Row],[شناسه ریسک]]),_xlfn._xlws.FILTER(r_actions[پیشرفت اجرا (%)],r_actions[شناسه ریسک]=Table1[[#This Row],[شناسه ریسک]]))} -> 0.62714493
A5: KH-RISK-4 | B5: =INDEX(r_detect[شرح ریسک],MATCH(Table1[[#This Row],[شناسه ریسک]],r_detect[کد ساختار شکست],0)) -> ریسک دارایی های فناورانه فاقد متولی | C5: منفی | D5: =INDEX(r_detect[طبقه بندی ریسک],MATCH(Table1[[#This Row],[شناسه ریسک]],r_detect[کد ساختار شکست],0)) -> دارایی های داخلی | E5: =INDEX(r_measure[شدت اثر فعلی],MATCH(Table1[[#This Row],[شناسه ریسک]],r_measure[شناسه ریسک],0)) -> متوسط | F5: =INDEX(r_measure[احتمال وقوع فعلی],MATCH(Table1[[#This Row],[شناسه ریسک]],r_measure[شناسه ریسک],0)) -> بعید | G5: =INDEX('Heat Map'!$B$3:$F$7, MATCH(E5,'Heat Map'!$A$3:$A$7, 0), MATCH(F5,'Heat Map'!$B$2:$F$2, 0)) -> Medium | H5: =INDEX(r_measure[شدت اثر هدف],MATCH(Table1[[#This Row],[شناسه ریسک]],r_measure[شناسه ریسک],0)) -> جزئی | I5: =INDEX(r_measure[احتمال وقوع هدف],MATCH(Table1[[#This Row],[شناسه ریسک]],r_measure[شناسه ریسک],0)) -> محتمل | J5: =INDEX('Heat Map'!$B$3:$F$7, MATCH(H5,'Heat Map'!$A$11:$A$15, 0), MATCH(I5,'Heat Map'!$B$10:$F$10, 0)) -> Medium | K5: {=SUMPRODUCT(_xlfn._xlws.FILTER(r_actions[پیشرفت فیزیکی],r_actions[شناسه ریسک]=Table1[[#This Row],[شناسه ریسک]]),_xlfn._xlws.FILTER(r_actions[پیشرفت اجرا (%)],r_actions[شناسه ریسک]=Table1[[#This Row],[شناسه ریسک]]))} -> 0.17812301
A6: KH-RISK-5 | B6: =INDEX(r_detect[شرح ریسک],MATCH(Table1[[#This Row],[شناسه ریسک]],r_detect[کد ساختار شکست],0)) -> ریسک از بین رفتن دانش، مستندات و نمونه ها | C6: منفی | D6: =INDEX(r_detect[طبقه بندی ریسک],MATCH(Table1[[#This Row],[شناسه ریسک]],r_detect[کد ساختار شکست],0)) -> دارایی های داخلی | E6: =INDEX(r_measure[شدت اثر فعلی],MATCH(Table1[[#This Row],[شناسه ریسک]],r_measure[شناسه ریسک],0)) -> ناچیز | F6: =INDEX(r_measure[احتمال وقوع فعلی],MATCH(Table1[[#This Row],[شناسه ریسک]],r_measure[شناسه ریسک],0)) -> بعید | G6: =INDEX('Heat Map'!$B$3:$F$7, MATCH(E6,'Heat Map'!$A$3:$A$7, 0), MATCH(F6,'Heat Map'!$B$2:$F$2, 0)) -> Low | H6: =INDEX(r_measure[شدت اثر هدف],MATCH(Table1[[#This Row],[شناسه ریسک]],r_measure[شناسه ریسک],0)) -> ناچیز | I6: =INDEX(r_measure[احتمال وقوع هدف],MATCH(Table1[[#This Row],[شناسه ریسک]],r_measure[شناسه ریسک],0)) -> مکرر | J6: =INDEX('Heat Map'!$B$3:$F$7, MATCH(H6,'Heat Map'!$A$11:$A$15, 0), MATCH(I6,'Heat Map'!$B$10:$F$10, 0)) -> Medium | K6: {=SUMPRODUCT(_xlfn._xlws.FILTER(r_actions[پیشرفت فیزیکی],r_actions[شناسه ریسک]=Table1[[#This Row],[شناسه ریسک]]),_xlfn._xlws.FILTER(r_actions[پیشرفت اجرا (%)],r_actions[شناسه ریسک]=Table1[[#This Row],[شناسه ریسک]]))} -> 0.29330247
A7: KH-RISK-6 | B7: =INDEX(r_detect[شرح ریسک],MATCH(Table1[[#This Row],[شناسه ریسک]],r_detect[کد ساختار شکست],0)) -> ریسک طبقه بندی نادرست دارایی ها (ارزش، بلوغ، فوریت) | C7: منفی | D7: =INDEX(r_detect[طبقه بندی ریسک],MATCH(Table1[[#This Row],[شناسه ریسک]],r_detect[کد ساختار شکست],0)) -> دارایی های داخلی | E7: =INDEX(r_measure[شدت اثر فعلی],MATCH(Table1[[#This Row],[شناسه ریسک]],r_measure[شناسه ریسک],0)) -> جزئی | F7: =INDEX(r_measure[احتمال وقوع فعلی],MATCH(Table1[[#This Row],[شناسه ریسک]],r_measure[شناسه ریسک],0)) -> بعید | G7: =INDEX('Heat Map'!$B$3:$F$7, MATCH(E7,'Heat Map'!$A$3:$A$7, 0), MATCH(F7,'Heat Map'!$B$2:$F$2, 0)) -> Medium | H7: =INDEX(r_measure[شدت اثر هدف],MATCH(Table1[[#This Row],[شناسه ریسک]],r_measure[شناسه ریسک],0)) -> اساسی | I7: =INDEX(r_measure[احتمال وقوع هدف],MATCH(Table1[[#This Row],[شناسه ریسک]],r_measure[شناسه ریسک],0)) -> بعید | J7: =INDEX('Heat Map'!$B$3:$F$7, MATCH(H7,'Heat Map'!$A$11:$A$15, 0), MATCH(I7,'Heat Map'!$B$10:$F$10, 0)) -> Medium | K7: {=SUMPRODUCT(_xlfn._xlws.FILTER(r_actions[پیشرفت فیزیکی],r_actions[شناسه ریسک]=Table1[[#This Row],[شناسه ریسک]]),_xlfn._xlws.FILTER(r_actions[پیشرفت اجرا (%)],r_actions[شناسه ریسک]=Table1[[#This Row],[شناسه ریسک]]))} -> 0.14463288
A8: KH-RISK-7 | B8: =INDEX(r_detect[شرح ریسک],MATCH(Table1[[#This Row],[شناسه ریسک]],r_detect[کد ساختار شکست],0)) -> ریسک تمایلی نداشتن به رها کردن مالکیت دارایی توسط واحدهای سازمانی | C8: منفی | D8: =INDEX(r_detect[طبقه بندی ریسک],MATCH(Table1[[#This Row],[شناسه ریسک]],r_detect[کد ساختار شکست],0)) -> دارایی های داخلی | E8: =INDEX(r_measure[شدت اثر فعلی],MATCH(Table1[[#This Row],[شناسه ریسک]],r_measure[شناسه ریسک],0)) -> عمده | F8: =INDEX(r_measure[احتمال وقوع فعلی],MATCH(Table1[[#This Row],[شناسه ریسک]],r_measure[شناسه ریسک],0)) -> نادر | G8: =INDEX('Heat Map'!$B$3:$F$7, MATCH(E8,'Heat Map'!$A$3:$A$7, 0), MATCH(F8,'Heat Map'!$B$2:$F$2, 0)) -> Low | H8: =INDEX(r_measure[شدت اثر هدف],MATCH(Table1[[#This Row],[شناسه ریسک]],r_measure[شناسه ریسک],0)) -> عمده | I8: =INDEX(r_measure[احتمال وقوع هدف],MATCH(Table1[[#This Row],[شناسه ریسک]],r_measure[شناسه ریسک],0)) -> نادر | J8: =INDEX('Heat Map'!$B$3:$F$7, MATCH(H8,'Heat Map'!$A$11:$A$15, 0), MATCH(I8,'Heat Map'!$B$10:$F$10, 0)) -> Low | K8: {=SUMPRODUCT(_xlfn._xlws.FILTER(r_actions[پیشرفت فیزیکی],r_actions[شناسه ریسک]=Table1[[#This Row],[شناسه ریسک]]),_xlfn._xlws.FILTER(r_actions[پیشرفت اجرا (%)],r_actions[شناسه ریسک]=Table1[[#This Row],[شناسه ریسک]]))} -> 0.15793589
A9: KH-RISK-8 | B9: =INDEX(r_detect[شرح ریسک],MATCH(Table1[[#This Row],[شناسه ریسک]],r_detect[کد ساختار شکست],0)) -> ریسک بسیار تخصصی دارایی های توسعه یافته و بواسطه آن بازار خارجی محدود | C9: منفی | D9: =INDEX(r_detect[طبقه بندی ریسک],MATCH(Table1[[#This Row],[شناسه ریسک]],r_detect[کد ساختار شکست],0)) -> دارایی های داخلی | E9: =INDEX(r_measure[شدت اثر فعلی],MATCH(Table1[[#This Row],[شناسه ریسک]],r_measure[شناسه ریسک],0)) -> ناچیز | F9: =INDEX(r_measure[احتمال وقوع فعلی],MATCH(Table1[[#This Row],[شناسه ریسک]],r_measure[شناسه ریسک],0)) -> ممکن | G9: =INDEX('Heat Map'!$B$3:$F$7, MATCH(E9,'Heat Map'!$A$3:$A$7, 0), MATCH(F9,'Heat Map'!$B$2:$F$2, 0)) -> Low | H9: =INDEX(r_measure[شدت اثر هدف],MATCH(Table1[[#This Row],[شناسه ریسک]],r_measure[شناسه ریسک],0)) -> متوسط | I9: =INDEX(r_measure[احتمال وقوع هدف],MATCH(Table1[[#This Row],[شناسه ریسک]],r_measure[شناسه ریسک],0)) -> ممکن | J9: =INDEX('Heat Map'!$B$3:$F$7, MATCH(H9,'Heat Map'!$A$11:$A$15, 0), MATCH(I9,'Heat Map'!$B$10:$F$10, 0)) -> Medium | K9: {=SUMPRODUCT(_xlfn._xlws.FILTER(r_actions[پیشرفت فیزیکی],r_actions[شناسه ریسک]=Table1[[#This Row],[شناسه ریسک]]),_xlfn._xlws.FILTER(r_actions[پیشرفت اجرا (%)],r_actions[شناسه ریسک]=Table1[[#This Row],[شناسه ریسک]]))} -> 0.4050011
A10: KH-RISK-9 | B10: =INDEX(r_detect[شرح ریسک],MATCH(Table1[[#This Row],[شناسه ریسک]],r_detect[کد ساختار شکست],0)) -> ریسک قدیمی بودن دارایی ها و نیازمند به روزرسانی های پرهزینه جهت استانداردسازی | C10: منفی | D10: =INDEX(r_detect[طبقه بندی ریسک],MATCH(Table1[[#This Row],[شناسه ریسک]],r_detect[کد ساختار شکست],0)) -> دارایی های داخلی | E10: =INDEX(r_measure[شدت اثر فعلی],MATCH(Table1[[#This Row],[شناسه ریسک]],r_measure[شناسه ریسک],0)) -> اساسی | F10: =INDEX(r_measure[احتمال وقوع فعلی],MATCH(Table1[[#This Row],[شناسه ریسک]],r_measure[شناسه ریسک],0)) -> محتمل | G10: =INDEX('Heat Map'!$B$3:$F$7, MATCH(E10,'Heat Map'!$A$3:$A$7, 0), MATCH(F10,'Heat Map'!$B$2:$F$2, 0)) -> Critical | H10: =INDEX(r_measure[شدت اثر هدف],MATCH(Table1[[#This Row],[شناسه ریسک]],r_measure[شناسه ریسک],0)) -> جزئی | I10: =INDEX(r_measure[احتمال وقوع هدف],MATCH(Table1[[#This Row],[شناسه ریسک]],r_measure[شناسه ریسک],0)) -> محتمل | J10: =INDEX('Heat Map'!$B$3:$F$7, MATCH(H10,'Heat Map'!$A$11:$A$15, 0), MATCH(I10,'Heat Map'!$B$10:$F$10, 0)) -> Medium | K10: {=SUMPRODUCT(_xlfn._xlws.FILTER(r_actions[پیشرفت فیزیکی],r_actions[شناسه ریسک]=Table1[[#This Row],[شناسه ریسک]]),_xlfn._xlws.FILTER(r_actions[پیشرفت اجرا (%)],r_actions[شناسه ریسک]=Table1[[#This Row],[شناسه ریسک]]))} -> 0.17320274
A11: KH-RISK-10 | B11: =INDEX(r_detect[شرح ریسک],MATCH(Table1[[#This Row],[شناسه ریسک]],r_detect[کد ساختار شکست],0)) -> ریسک اعتبار فناورانه و مالی شریک | C11: منفی | D11: =INDEX(r_detect[طبقه بندی ریسک],MATCH(Table1[[#This Row],[شناسه ریسک]],r_detect[کد ساختار شکست],0)) -> همکاری های بیرونی | E11: =INDEX(r_measure[شدت اثر فعلی],MATCH(Table1[[#This Row],[شناسه ریسک]],r_measure[شناسه ریسک],0)) -> اساسی | F11: =INDEX(r_measure[احتمال وقوع فعلی],MATCH(Table1[[#This Row],[شناسه ریسک]],r_measure[شناسه ریسک],0)) -> مکرر | G11: =INDEX('Heat Map'!$B$3:$F$7, MATCH(E11,'Heat Map'!$A$3:$A$7, 0), MATCH(F11,'Heat Map'!$B$2:$F$2, 0)) -> Critical | H11: =INDEX(r_measure[شدت اثر هدف],MATCH(Table1[[#This Row],[شناسه ریسک]],r_measure[شناسه ریسک],0)) -> ناچیز | I11: =INDEX(r_measure[احتمال وقوع هدف],MATCH(Table1[[#This Row],[شناسه ریسک]],r_measure[شناسه ریسک],0)) -> مکرر | J11: =INDEX('Heat Map'!$B$3:$F$7, MATCH(H11,'Heat Map'!$A$11:$A$15, 0), MATCH(I11,'Heat Map'!$B$10:$F$10, 0)) -> Medium | K11: {=SUMPRODUCT(_xlfn._xlws.FILTER(r_actions[پیشرفت فیزیکی],r_actions[شناسه ریسک]=Table1[[#This Row],[شناسه ریسک]]),_xlfn._xlws.FILTER(r_actions[پیشرفت اجرا (%)],r_actions[شناسه ریسک]=Table1[[#This Row],[شناسه ریسک]]))} -> 0.15793589
A12: KH-RISK-11 | B12: =INDEX(r_detect[شرح ریسک],MATCH(Table1[[#This Row],[شناسه ریسک]],r_detect[کد ساختار شکست],0)) -> ریسک های حقوقی، قراردادی و مالکیتی در مشارکت | C12: منفی | D12: =INDEX(r_detect[طبقه بندی ریسک],MATCH(Table1[[#This Row],[شناسه ریسک]],r_detect[کد ساختار شکست],0)) -> همکاری های بیرونی | E12: =INDEX(r_measure[شدت اثر فعلی],MATCH(Table1[[#This Row],[شناسه ریسک]],r_measure[شناسه ریسک],0)) -> عمده | F12: =INDEX(r_measure[احتمال وقوع فعلی],MATCH(Table1[[#This Row],[شناسه ریسک]],r_measure[شناسه ریسک],0)) -> مکرر | G12: =INDEX('Heat Map'!$B$3:$F$7, MATCH(E12,'Heat Map'!$A$3:$A$7, 0), MATCH(F12,'Heat Map'!$B$2:$F$2, 0)) -> Critical | H12: =INDEX(r_measure[شدت اثر هدف],MATCH(Table1[[#This Row],[شناسه ریسک]],r_measure[شناسه ریسک],0)) -> اساسی | I12: =INDEX(r_measure[احتمال وقوع هدف],MATCH(Table1[[#This Row],[شناسه ریسک]],r_measure[شناسه ریسک],0)) -> بعید | J12: =INDEX('Heat Map'!$B$3:$F$7, MATCH(H12,'Heat Map'!$A$11:$A$15, 0), MATCH(I12,'Heat Map'!$B$10:$F$10, 0)) -> Medium | K12: {=SUMPRODUCT(_xlfn._xlws.FILTER(r_actions[پیشرفت فیزیکی],r_actions[شناسه ریسک]=Table1[[#This Row],[شناسه ریسک]]),_xlfn._xlws.FILTER(r_actions[پیشرفت اجرا (%)],r_actions[شناسه ریسک]=Table1[[#This Row],[شناسه ریسک]]))} -> 0.4050011
A13: KH-RISK-12 | B13: =INDEX(r_detect[شرح ریسک],MATCH(Table1[[#This Row],[شناسه ریسک]],r_detect[کد ساختار شکست],0)) -> ریسک عدم هم راستایی اهداف شریک با منافع خوارزمی | C13: منفی | D13: =INDEX(r_detect[طبقه بندی ریسک],MATCH(Table1[[#This Row],[شناسه ریسک]],r_detect[کد ساختار شکست],0)) -> همکاری های بیرونی | E13: =INDEX(r_measure[شدت اثر فعلی],MATCH(Table1[[#This Row],[شناسه ریسک]],r_measure[شناسه ریسک],0)) -> متوسط | F13: =INDEX(r_measure[احتمال وقوع فعلی],MATCH(Table1[[#This Row],[شناسه ریسک]],r_measure[شناسه ریسک],0)) -> مکرر | G13: =INDEX('Heat Map'!$B$3:$F$7, MATCH(E13,'Heat Map'!$A$3:$A$7, 0), MATCH(F13,'Heat Map'!$B$2:$F$2, 0)) -> High | H13: =INDEX(r_measure[شدت اثر هدف],MATCH(Table1[[#This Row],[شناسه ریسک]],r_measure[شناسه ریسک],0)) -> عمده | I13: =INDEX(r_measure[احتمال وقوع هدف],MATCH(Table1[[#This Row],[شناسه ریسک]],r_measure[شناسه ریسک],0)) -> نادر | J13: =INDEX('Heat Map'!$B$3:$F$7, MATCH(H13,'Heat Map'!$A$11:$A$15, 0), MATCH(I13,'Heat Map'!$B$10:$F$10, 0)) -> Low | K13: {=SUMPRODUCT(_xlfn._xlws.FILTER(r_actions[پیشرفت فیزیکی],r_actions[شناسه ریسک]=Table1[[#This Row],[شناسه ریسک]]),_xlfn._xlws.FILTER(r_actions[پیشرفت اجرا (%)],r_actions[شناسه ریسک]=Table1[[#This Row],[شناسه ریسک]]))} -> 0.7746
... A23: KH-RISK-22 | B23: =INDEX(r_detect[شرح ریسک],MATCH(Table1[[#This Row],[شناسه ریسک]],r_detect[کد ساختار شکست],0)) -> پتانسیل توسعه جریان‌های درآمدی جدید بواسطه نوآورانه بودن طرح کسب‌وکار خوارزمی | C23: مثبت | D23: =INDEX(r_detect[طبقه بندی ریسک],MATCH(Table1[[#This Row],[شناسه ریسک]],r_detect[کد ساختار شکست],0)) -> پایداری و خدمات | E23: =INDEX(r_measure[شدت اثر فعلی],MATCH(Table1[[#This Row],[شناسه ریسک]],r_measure[شناسه ریسک],0)) -> جزئی | F23: =INDEX(r_measure[احتمال وقوع فعلی],MATCH(Table1[[#This Row],[شناسه ریسک]],r_measure[شناسه ریسک],0)) -> نادر | G23: =INDEX('Heat Map'!$B$3:$F$7, MATCH(E23,'Heat Map'!$A$3:$A$7, 0), MATCH(F23,'Heat Map'!$B$2:$F$2, 0)) -> Low | H23: =INDEX(r_measure[شدت اثر هدف],MATCH(Table1[[#This Row],[شناسه ریسک]],r_measure[شناسه ریسک],0)) -> عمده | I23: =INDEX(r_measure[احتمال وقوع هدف],MATCH(Table1[[#This Row],[شناسه ریسک]],r_measure[شناسه ریسک],0)) -> محتمل | J23: =INDEX('Heat Map'!$B$3:$F$7, MATCH(H23,'Heat Map'!$A$11:$A$15, 0), MATCH(I23,'Heat Map'!$B$10:$F$10, 0)) -> Critical | K23: {=SUMPRODUCT(_xlfn._xlws.FILTER(r_actions[پیشرفت فیزیکی],r_actions[شناسه ریسک]=Table1[[#This Row],[شناسه ریسک]]),_xlfn._xlws.FILTER(r_actions[پیشرفت اجرا (%)],r_actions[شناسه ریسک]=Table1[[#This Row],[شناسه ریسک]]))} -> 0.20134137

Sheet داشبورد
A1: خلاصه ریسک‌ها منفی
A2: سطح ریسک فعلی | B2: تعداد | F2: طبقه بندی ریسک | G2: تعداد | I2: وضعیت اقدامات | J2: میانگین پیشرفت (%)
A3: Low | B3: =COUNTIFS(Table1[سطح فعلی ریسک], A3,Table1[تأثیر],"منفی")/COUNTIF(Table1[تأثیر],"منفی") -> 0.22222222 | C3: 0.1 | E3: =SUMPRODUCT(B3:B6,$C$3:$C$6) -> 0.25 | F3: همکاری های بیرونی | G3: =COUNTIF(ارزیابی!$D$2:$D$23, "همکاری های بیرونی") -> 3 | I3: کل اقدامات | J3: =COUNTA(r_actions[شرح اقدام]) -> 88
A4: Medium | B4: =COUNTIFS(Table1[سطح فعلی ریسک], A4,Table1[تأثیر],"منفی")/COUNTIF(Table1[تأثیر],"منفی") -> 0.33333333 | C4: 0.2 | F4: پایداری و خدمات | G4: =COUNTIF(ارزیابی!$D$2:$D$23, "پایداری و خدمات") -> 4 | I4: میانگین پیشرفت | J4: =AVERAGE(r_actions[پیشرفت اجرا (%)]) -> 0.53909091
A5: High | B5: =COUNTIFS(Table1[سطح فعلی ریسک], A5,Table1[تأثیر],"منفی")/COUNTIF(Table1[تأثیر],"منفی") -> 0.16666667 | C5: 0.3 | F5: حکمرانی | G5: =COUNTIF(ارزیابی!$D$2:$D$23, "حکمرانی") -> 6
A6: Critical | B6: =COUNTIFS(Table1[سطح فعلی ریسک], A6,Table1[تأثیر],"منفی")/COUNTIF(Table1[تأثیر],"منفی") -> 0.27777778 | C6: 0.4 | F6: دارایی های داخلی | G6: =COUNTIF(ارزیابی!$D$2:$D$23, "دارایی های داخلی") -> 6
A7: سطح ریسک هدف | B7: تعداد | F7: مرجعیت فکری | G7: =COUNTIF(ارزیابی!$D$2:$D$23, "مرجعیت فکری") -> 3
A8: Low | B8: =COUNTIFS(Table1[سطح هدف ریسک], A8,Table1[تأثیر],"منفی")/COUNTIF(Table1[تأثیر],"منفی") -> 0.22222222 | E8: =SUMPRODUCT(B8:B11,$C$3:$C$6) -> 0.17777778
A9: Medium | B9: =COUNTIFS(Table1[سطح هدف ریسک], A9,Table1[تأثیر],"منفی")/COUNTIF(Table1[تأثیر],"منفی") -> 0.77777778
A10: High | B10: =COUNTIFS(Table1[سطح هدف ریسک], A10,Table1[تأثیر],"منفی")/COUNTIF(Table1[تأثیر],"منفی") -> 0
A11: Critical | B11: =COUNTIFS(Table1[سطح هدف ریسک], A11,Table1[تأثیر],"منفی")/COUNTIF(Table1[تأثیر],"منفی") -> 0
A12: خلاصه ریسک‌ها مثبت
A13: سطح ریسک فعلی | C13: 0.1 | E13: =SUMPRODUCT(B14:B17,C13:C16) -> 0.2
A14: Low | B14: =COUNTIFS(Table1[سطح فعلی ریسک], A14,Table1[تأثیر],"مثبت")/COUNTIF(Table1[تأثیر],"مثبت") -> 0.5 | C14: 0.2
A15: Medium | B15: =COUNTIFS(Table1[سطح فعلی ریسک], A15,Table1[تأثیر],"مثبت")/COUNTIF(Table1[تأثیر],"مثبت") -> 0.25 | C15: 0.3
A16: High | B16: =COUNTIFS(Table1[سطح فعلی ریسک], A16,Table1[تأثیر],"مثبت")/COUNTIF(Table1[تأثیر],"مثبت") -> 0 | C16: 0.4
A17: Critical | B17: =COUNTIFS(Table1[سطح فعلی ریسک], A17,Table1[تأثیر],"مثبت")/COUNTIF(Table1[تأثیر],"مثبت") -> 0.25
A18: سطح ریسک هدف | B18: تعداد
A19: Low | B19: =COUNTIFS(Table1[سطح هدف ریسک], A19,Table1[تأثیر],"مثبت")/COUNTIF(Table1[تأثیر],"مثبت") -> 0 | E19: =SUMPRODUCT(B19:B22,$C$3:$C$6) -> 0.3
A20: Medium | B20: =COUNTIFS(Table1[سطح هدف ریسک], A20,Table1[تأثیر],"مثبت")/COUNTIF(Table1[تأثیر],"مثبت") -> 0.5
A21: High | B21: =COUNTIFS(Table1[سطح هدف ریسک], A21,Table1[تأثیر],"مثبت")/COUNTIF(Table1[تأثیر],"مثبت") -> 0
A22: Critical | B22: =COUNTIFS(Table1[سطح هدف ریسک], A22,Table1[تأثیر],"مثبت")/COUNTIF(Table1[تأثیر],"مثبت") -> 0.5
C46: =B47/SUM($B$47:$B$50) -> 0.23978202
A47: فروردین | B47: =SUMIF(r_actions[ماه/بازه],داشبورد!A47,r_actions[اهمیت (1-10)]) -> 88 | C47: =B48/SUM($B$47:$B$50) -> 0.24250681
A48: اردیبهشت | B48: =SUMIF(r_actions[ماه/بازه],داشبورد!A48,r_actions[اهمیت (1-10)]) -> 89 | C48: =B49/SUM($B$47:$B$50) -> 0.23160763
A49: خرداد | B49: =SUMIF(r_actions[ماه/بازه],داشبورد!A49,r_actions[اهمیت (1-10)]) -> 85 | C49: =B50/SUM($B$47:$B$50) -> 0.28610354
A50: تیر تا اسفند | B50: =SUMIF(r_actions[ماه/بازه],داشبورد!A50,r_actions[اهمیت (1-10)]) -> 105

Sheet Gauge Charts
B1: Opp. Value | E1: Risk Value
A2: Value | B2: 0.1 | C2: 1 | D2: Value | E2: 0.1 | F2: 1
A3: Remainder | B3: 0.2 | C3: 1 | D3: Remainder | E3: 0.2 | F3: 1
B4: 0.3 | C4: 1 | E4: 0.3 | F4: 1
B5: 0.4 | C5: 1 | E5: 0.4 | F5: 1
B6: 0.5 | C6: 1 | E6: 0.5 | F6: 1
B7: 0.6 | C7: 1 | E7: 0.6 | F7: 1
B8: 0.7 | C8: 1 | E8: 0.7 | F8: 1
B9: 0.8 | C9: 1 | E9: 0.8 | F9: 1
B10: 0.9 | C10: 1 | E10: 0.9 | F10: 1
B11: 1 | C11: 9 | E11: 1 | F11: 9
B15: =B19*PI() -> 0.78539816 | D15: =D19*PI() -> 0.55850536 | F15: =F19*PI() -> 0.62831853 | H15: =H19*PI() -> 0.9424778
B16: x | C16: y | D16: x | E16: y | F16: x | G16: y | H16: x | I16: y
B17: 0 | C17: 0 | D17: 0 | E17: 0 | F17: 0 | G17: 0 | H17: 0 | I17: 0
B18: =COS(B15)*-1 -> -0.70710678 | C18: =SIN(B15) -> 0.70710678 | D18: =COS(D15)*-1 -> -0.8480481 | E18: =SIN(D15) -> 0.52991926 | F18: =COS(F15)*-1 -> -0.80901699 | G18: =SIN(F15) -> 0.58778525 | H18: =COS(H15)*-1 -> -0.58778525 | I18: =SIN(H15) -> 0.80901699
B19: =داشبورد!E3 -> 0.25 | D19: =داشبورد!E8 -> 0.17777778 | F19: =داشبورد!E13 -> 0.2 | H19: =داشبورد!E19 -> 0.3
